{
  "skill": {
    "name": "omanut-ai",
    "description": "Connect to Omanut AI platform — manage conversations, customers, tickets, media, analytics, AI training, content scheduling, image/video generation, and brand alignment.",
    "transport": "streamable-http",
    "url": "https://dzheddvoiauevcayifev.supabase.co/functions/v1/mcp-server",
    "headers": {
      "x-api-key": "YOUR_API_KEY_HERE"
    }
  },
  "tools_overview": {
    "conversations": {
      "list_conversations": "List recent customer conversations with filters",
      "get_conversation": "Get full conversation with all messages for analysis"
    },
    "analytics": {
      "get_analytics": "Business metrics: conversations, revenue, reservations",
      "list_customers": "Customer segments with engagement and conversion scores"
    },
    "ai_quality": {
      "get_ai_config": "Current AI model, temperature, prompt, and tool settings",
      "list_ai_errors": "AI error logs — hallucinations, misroutes, quality issues"
    },
    "knowledge": {
      "search_knowledge_base": "Search company documents by keyword",
      "update_knowledge_base": "Add or update knowledge base documents"
    },
    "content_scheduling": {
      "list_scheduled_posts": "List posts by status: pending_approval, approved, published, failed",
      "review_scheduled_post": "Approve, reject, or edit a scheduled post — content approval agent",
      "create_scheduled_post": "Create a new post with caption, image, platform, and timing"
    },
    "image_generation": {
      "list_generated_images": "Audit AI-generated images: prompts, approval status, brand assets used",
      "get_image_generation_settings": "Read style, tone, brand colors, visual guidelines",
      "update_image_generation_settings": "Tune style/tone/colors to fix brand drift"
    },
    "brand_identity": {
      "list_product_identity_profiles": "Audit product fingerprints: hex colors, labels, exclusion keywords",
      "update_product_identity_profile": "Fix brand alignment: edit exclusions, colors, labels"
    },
    "video_generation": {
      "list_video_jobs": "Monitor video jobs: status, provider, aspect ratio, failures"
    },
    "operations": {
      "send_message": "Send WhatsApp message to a customer",
      "list_tickets": "List support tickets",
      "create_ticket": "Create a new support ticket",
      "list_reservations": "List reservations/bookings",
      "list_products": "List active payment products",
      "list_media": "List company media assets",
      "get_company_info": "Company profile and settings"
    }
  },
  "setup_instructions": [
    "1. Generate an API key in the Omanut dashboard (Settings → API Keys)",
    "2. Replace YOUR_API_KEY_HERE with your key",
    "3. Save this file to ~/.openclaw/skills/omanut-ai.json",
    "4. Restart OpenClaw to load the skill"
  ]
}
